{
  "CUPOM10OFF": {"tipo": "percentual", "valor": 0.10, "maxDesconto": 999.00},
  "CUPOM50FIXO": {"tipo": "fixo", "valor": 50.00},
"CUPOM05": {"tipo": "percentual", "valor": 0.05},
"CUPOM10": {"tipo": "percentual", "valor": 0.10},
"CUPOM15": {"tipo": "percentual", "valor": 0.15},
"CUPOM20": {"tipo": "percentual", "valor": 0.20},
"CUPOM25": {"tipo": "percentual", "valor": 0.25},
"CUPOM30": {"tipo": "percentual", "valor": 0.30},
"CUPOM35": {"tipo": "percentual", "valor": 0.35},
"CUPOM40": {"tipo": "percentual", "valor": 0.40},
"CUPOM45": {"tipo": "percentual", "valor": 0.45},
"CUPOM50": {"tipo": "percentual", "valor": 0.50},
"CUPOM55": {"tipo": "percentual", "valor": 0.55},
"CUPOM60": {"tipo": "percentual", "valor": 0.60},
"CUPOM65": {"tipo": "percentual", "valor": 0.65},
"CUPOM70": {"tipo": "percentual", "valor": 0.70},
"CUPOM75": {"tipo": "percentual", "valor": 0.75},
"CUPOM80": {"tipo": "percentual", "valor": 0.80},
"CUPOM85": {"tipo": "percentual", "valor": 0.85},
"CUPOM90": {"tipo": "percentual", "valor": 0.90},
"CUPOM95": {"tipo": "percentual", "valor": 0.95},
  "BOASVINDAS": {"tipo": "percentual", "valor": 0.15},
  "FILHOPROF10": {"tipo": "percentual", "valor": 0.10},
  "GANHE30": {"tipo": "fixo", "valor": 30.00}
}
